a7a1234.py
a7a1234-1.0.0.dist-info/METADATA
a7a1234-1.0.0.dist-info/WHEEL
a7a1234-1.0.0.dist-info/RECORD
