Metadata-Version: 2.1
Name: a7a1234
Version: 1.0.0
Summary: 
License: none
Author: firas
Requires-Python: >=3.10,<3.11
Classifier: License :: Other/Proprietary License
Classifier: Programming Language :: Python :: 3
Classifier: Programming Language :: Python :: 3.10
Requires-Dist: fastapi (==0.87.0)
Requires-Dist: httpx (==0.23.1)
Requires-Dist: loguru (==0.6.0)
Requires-Dist: pydantic (==1.10.2)
Requires-Dist: python-dotenv (==0.21.0)
Requires-Dist: python-multipart (==0.0.5)
Requires-Dist: pyyaml (==6.0)
Requires-Dist: starlette (==0.21.0)
Requires-Dist: uvicorn (==0.20.0)
